{
    "drawx": 96,
    "drawy": 96,
    "height": 12,
    "origins": [
        {
            "x": 3,
            "y": 7
        },
        {
            "x": 3,
            "y": 5
        },
        {
            "x": 3,
            "y": 4
        },
        {
            "x": 3,
            "y": 1
        }
    ],
    "spawn": [
        {
            "x": 4,
            "y": 1
        },
        {
            "x": 4,
            "y": 4
        },
        {
            "x": 4,
            "y": 5
        },
        {
            "x": 4,
            "y": 7
        },
        {
            "x": 4,
            "y": 8
        },
        {
            "x": 4,
            "y": 10
        }
    ],
    "tiles": [
        [
            {
                "asset": "ROCK",
                "id": -1,
                "lifetime": -1,
                "occupant": "NONE",
                "temporary_asset": "NONE",
                "type": "OBSTACLE"
            },
            {
                "asset": "ROCK",
                "id": -1,
                "lifetime": -1,
                "occupant": "NONE",
                "temporary_asset": "NONE",
                "type": "OBSTACLE"
            },
            {
                "asset": "NONE",
                "id": -1,
                "lifetime": -1,
                "occupant": "NONE",
                "temporary_asset": "NONE",
                "type": "PASSABLE"
            },
            {
                "asset": "NONE",
                "id": -1,
                "lifetime": -1,
                "occupant": "NONE",
                "temporary_asset": "NONE",
                "type": "PASSABLE"
            },
            {
                "asset": "IMPASSABLE",
                "id": -1,
                "lifetime": -1,
                "occupant": "NONE",
                "temporary_asset": "NONE",
                "type": "ENEMY PASSABLE"
            },
            {
                "asset": "IMPASSABLE",
                "id": -1,
                "lifetime": -1,
                "occupant": "NONE",
                "temporary_asset": "NONE",
                "type": "ENEMY PASSABLE"
            },
            {
                "asset": "IMPASSABLE",
                "id": -1,
                "lifetime": -1,
                "occupant": "NONE",
                "temporary_asset": "NONE",
                "type": "ENEMY PASSABLE"
            }
        ],
        [
            {
                "asset": "ROCK",
                "id": -1,
                "lifetime": -1,
                "occupant": "NONE",
                "temporary_asset": "NONE",
                "type": "OBSTACLE"
            },
            {
                "asset": "ROCK",
                "id": -1,
                "lifetime": -1,
                "occupant": "NONE",
                "temporary_asset": "NONE",
                "type": "OBSTACLE"
            },
            {
                "asset": "NONE",
                "id": -1,
                "lifetime": -1,
                "occupant": "NONE",
                "temporary_asset": "NONE",
                "type": "PASSABLE"
            },
            {
                "asset": "NONE",
                "id": -1,
                "lifetime": -1,
                "occupant": "NONE",
                "temporary_asset": "NONE",
                "type": "PASSABLE"
            },
            {
                "asset": "IMPASSABLE",
                "id": -1,
                "lifetime": -1,
                "occupant": "NONE",
                "temporary_asset": "NONE",
                "type": "ENEMY PASSABLE"
            },
            {
                "asset": "IMPASSABLE",
                "id": -1,
                "lifetime": -1,
                "occupant": "NONE",
                "temporary_asset": "NONE",
                "type": "ENEMY PASSABLE"
            },
            {
                "asset": "IMPASSABLE",
                "id": -1,
                "lifetime": -1,
                "occupant": "NONE",
                "temporary_asset": "NONE",
                "type": "ENEMY PASSABLE"
            }
        ],
        [
            {
                "asset": "ROCK",
                "id": -1,
                "lifetime": -1,
                "occupant": "NONE",
                "temporary_asset": "NONE",
                "type": "OBSTACLE"
            },
            {
                "asset": "ROCK",
                "id": -1,
                "lifetime": -1,
                "occupant": "NONE",
                "temporary_asset": "NONE",
                "type": "OBSTACLE"
            },
            {
                "asset": "NONE",
                "id": -1,
                "lifetime": -1,
                "occupant": "NONE",
                "temporary_asset": "NONE",
                "type": "PASSABLE"
            },
            {
                "asset": "ROCK",
                "id": -1,
                "lifetime": -1,
                "occupant": "NONE",
                "temporary_asset": "NONE",
                "type": "OBSTACLE"
            },
            {
                "asset": "IMPASSABLE",
                "id": -1,
                "lifetime": -1,
                "occupant": "NONE",
                "temporary_asset": "NONE",
                "type": "ENEMY PASSABLE"
            },
            {
                "asset": "IMPASSABLE",
                "id": -1,
                "lifetime": -1,
                "occupant": "NONE",
                "temporary_asset": "NONE",
                "type": "ENEMY PASSABLE"
            },
            {
                "asset": "IMPASSABLE",
                "id": -1,
                "lifetime": -1,
                "occupant": "NONE",
                "temporary_asset": "NONE",
                "type": "ENEMY PASSABLE"
            }
        ],
        [
            {
                "asset": "ROCK",
                "id": -1,
                "lifetime": -1,
                "occupant": "NONE",
                "temporary_asset": "NONE",
                "type": "OBSTACLE"
            },
            {
                "asset": "ROCK",
                "id": -1,
                "lifetime": -1,
                "occupant": "NONE",
                "temporary_asset": "NONE",
                "type": "OBSTACLE"
            },
            {
                "asset": "NONE",
                "id": -1,
                "lifetime": -1,
                "occupant": "NONE",
                "temporary_asset": "NONE",
                "type": "PASSABLE"
            },
            {
                "asset": "ROCK",
                "id": -1,
                "lifetime": -1,
                "occupant": "NONE",
                "temporary_asset": "NONE",
                "type": "OBSTACLE"
            },
            {
                "asset": "IMPASSABLE",
                "id": -1,
                "lifetime": -1,
                "occupant": "NONE",
                "temporary_asset": "NONE",
                "type": "ENEMY PASSABLE"
            },
            {
                "asset": "IMPASSABLE",
                "id": -1,
                "lifetime": -1,
                "occupant": "NONE",
                "temporary_asset": "NONE",
                "type": "ENEMY PASSABLE"
            },
            {
                "asset": "IMPASSABLE",
                "id": -1,
                "lifetime": -1,
                "occupant": "NONE",
                "temporary_asset": "NONE",
                "type": "ENEMY PASSABLE"
            }
        ],
        [
            {
                "asset": "ROCK",
                "id": -1,
                "lifetime": -1,
                "occupant": "NONE",
                "temporary_asset": "NONE",
                "type": "OBSTACLE"
            },
            {
                "asset": "ROCK",
                "id": -1,
                "lifetime": -1,
                "occupant": "NONE",
                "temporary_asset": "NONE",
                "type": "OBSTACLE"
            },
            {
                "asset": "NONE",
                "id": -1,
                "lifetime": -1,
                "occupant": "NONE",
                "temporary_asset": "NONE",
                "type": "PASSABLE"
            },
            {
                "asset": "NONE",
                "id": -1,
                "lifetime": -1,
                "occupant": "NONE",
                "temporary_asset": "NONE",
                "type": "PASSABLE"
            },
            {
                "asset": "IMPASSABLE",
                "id": -1,
                "lifetime": -1,
                "occupant": "NONE",
                "temporary_asset": "NONE",
                "type": "ENEMY PASSABLE"
            },
            {
                "asset": "IMPASSABLE",
                "id": -1,
                "lifetime": -1,
                "occupant": "NONE",
                "temporary_asset": "NONE",
                "type": "ENEMY PASSABLE"
            },
            {
                "asset": "IMPASSABLE",
                "id": -1,
                "lifetime": -1,
                "occupant": "NONE",
                "temporary_asset": "NONE",
                "type": "ENEMY PASSABLE"
            }
        ],
        [
            {
                "asset": "ROCK",
                "id": -1,
                "lifetime": -1,
                "occupant": "NONE",
                "temporary_asset": "NONE",
                "type": "OBSTACLE"
            },
            {
                "asset": "ROCK",
                "id": -1,
                "lifetime": -1,
                "occupant": "NONE",
                "temporary_asset": "NONE",
                "type": "OBSTACLE"
            },
            {
                "asset": "NONE",
                "id": -1,
                "lifetime": -1,
                "occupant": "NONE",
                "temporary_asset": "NONE",
                "type": "PASSABLE"
            },
            {
                "asset": "NONE",
                "id": -1,
                "lifetime": -1,
                "occupant": "NONE",
                "temporary_asset": "NONE",
                "type": "PASSABLE"
            },
            {
                "asset": "IMPASSABLE",
                "id": -1,
                "lifetime": -1,
                "occupant": "NONE",
                "temporary_asset": "NONE",
                "type": "ENEMY PASSABLE"
            },
            {
                "asset": "IMPASSABLE",
                "id": -1,
                "lifetime": -1,
                "occupant": "NONE",
                "temporary_asset": "NONE",
                "type": "ENEMY PASSABLE"
            },
            {
                "asset": "IMPASSABLE",
                "id": -1,
                "lifetime": -1,
                "occupant": "NONE",
                "temporary_asset": "NONE",
                "type": "ENEMY PASSABLE"
            }
        ],
        [
            {
                "asset": "ROCK",
                "id": -1,
                "lifetime": -1,
                "occupant": "NONE",
                "temporary_asset": "NONE",
                "type": "OBSTACLE"
            },
            {
                "asset": "ROCK",
                "id": -1,
                "lifetime": -1,
                "occupant": "NONE",
                "temporary_asset": "NONE",
                "type": "OBSTACLE"
            },
            {
                "asset": "NONE",
                "id": -1,
                "lifetime": -1,
                "occupant": "NONE",
                "temporary_asset": "NONE",
                "type": "PASSABLE"
            },
            {
                "asset": "ROCK",
                "id": -1,
                "lifetime": -1,
                "occupant": "NONE",
                "temporary_asset": "NONE",
                "type": "OBSTACLE"
            },
            {
                "asset": "IMPASSABLE",
                "id": -1,
                "lifetime": -1,
                "occupant": "NONE",
                "temporary_asset": "NONE",
                "type": "ENEMY PASSABLE"
            },
            {
                "asset": "IMPASSABLE",
                "id": -1,
                "lifetime": -1,
                "occupant": "NONE",
                "temporary_asset": "NONE",
                "type": "ENEMY PASSABLE"
            },
            {
                "asset": "IMPASSABLE",
                "id": -1,
                "lifetime": -1,
                "occupant": "NONE",
                "temporary_asset": "NONE",
                "type": "ENEMY PASSABLE"
            }
        ],
        [
            {
                "asset": "ROCK",
                "id": -1,
                "lifetime": -1,
                "occupant": "NONE",
                "temporary_asset": "NONE",
                "type": "OBSTACLE"
            },
            {
                "asset": "ROCK",
                "id": -1,
                "lifetime": -1,
                "occupant": "NONE",
                "temporary_asset": "NONE",
                "type": "OBSTACLE"
            },
            {
                "asset": "NONE",
                "id": -1,
                "lifetime": -1,
                "occupant": "NONE",
                "temporary_asset": "NONE",
                "type": "PASSABLE"
            },
            {
                "asset": "NONE",
                "id": -1,
                "lifetime": -1,
                "occupant": "NONE",
                "temporary_asset": "NONE",
                "type": "PASSABLE"
            },
            {
                "asset": "IMPASSABLE",
                "id": -1,
                "lifetime": -1,
                "occupant": "NONE",
                "temporary_asset": "NONE",
                "type": "ENEMY PASSABLE"
            },
            {
                "asset": "IMPASSABLE",
                "id": -1,
                "lifetime": -1,
                "occupant": "NONE",
                "temporary_asset": "NONE",
                "type": "ENEMY PASSABLE"
            },
            {
                "asset": "IMPASSABLE",
                "id": -1,
                "lifetime": -1,
                "occupant": "NONE",
                "temporary_asset": "NONE",
                "type": "ENEMY PASSABLE"
            }
        ],
        [
            {
                "asset": "ROCK",
                "id": -1,
                "lifetime": -1,
                "occupant": "NONE",
                "temporary_asset": "NONE",
                "type": "OBSTACLE"
            },
            {
                "asset": "ROCK",
                "id": -1,
                "lifetime": -1,
                "occupant": "NONE",
                "temporary_asset": "NONE",
                "type": "OBSTACLE"
            },
            {
                "asset": "NONE",
                "id": -1,
                "lifetime": -1,
                "occupant": "NONE",
                "temporary_asset": "NONE",
                "type": "PASSABLE"
            },
            {
                "asset": "NONE",
                "id": -1,
                "lifetime": -1,
                "occupant": "NONE",
                "temporary_asset": "NONE",
                "type": "PASSABLE"
            },
            {
                "asset": "IMPASSABLE",
                "id": -1,
                "lifetime": -1,
                "occupant": "NONE",
                "temporary_asset": "NONE",
                "type": "ENEMY PASSABLE"
            },
            {
                "asset": "IMPASSABLE",
                "id": -1,
                "lifetime": -1,
                "occupant": "NONE",
                "temporary_asset": "NONE",
                "type": "ENEMY PASSABLE"
            },
            {
                "asset": "IMPASSABLE",
                "id": -1,
                "lifetime": -1,
                "occupant": "NONE",
                "temporary_asset": "NONE",
                "type": "ENEMY PASSABLE"
            }
        ],
        [
            {
                "asset": "ROCK",
                "id": -1,
                "lifetime": -1,
                "occupant": "NONE",
                "temporary_asset": "NONE",
                "type": "OBSTACLE"
            },
            {
                "asset": "ROCK",
                "id": -1,
                "lifetime": -1,
                "occupant": "NONE",
                "temporary_asset": "NONE",
                "type": "OBSTACLE"
            },
            {
                "asset": "NONE",
                "id": -1,
                "lifetime": -1,
                "occupant": "NONE",
                "temporary_asset": "NONE",
                "type": "PASSABLE"
            },
            {
                "asset": "ROCK",
                "id": -1,
                "lifetime": -1,
                "occupant": "NONE",
                "temporary_asset": "NONE",
                "type": "OBSTACLE"
            },
            {
                "asset": "IMPASSABLE",
                "id": -1,
                "lifetime": -1,
                "occupant": "NONE",
                "temporary_asset": "NONE",
                "type": "ENEMY PASSABLE"
            },
            {
                "asset": "IMPASSABLE",
                "id": -1,
                "lifetime": -1,
                "occupant": "NONE",
                "temporary_asset": "NONE",
                "type": "ENEMY PASSABLE"
            },
            {
                "asset": "IMPASSABLE",
                "id": -1,
                "lifetime": -1,
                "occupant": "NONE",
                "temporary_asset": "NONE",
                "type": "ENEMY PASSABLE"
            }
        ],
        [
            {
                "asset": "ROCK",
                "id": -1,
                "lifetime": -1,
                "occupant": "NONE",
                "temporary_asset": "NONE",
                "type": "OBSTACLE"
            },
            {
                "asset": "ROCK",
                "id": -1,
                "lifetime": -1,
                "occupant": "NONE",
                "temporary_asset": "NONE",
                "type": "OBSTACLE"
            },
            {
                "asset": "NONE",
                "id": -1,
                "lifetime": -1,
                "occupant": "NONE",
                "temporary_asset": "NONE",
                "type": "PASSABLE"
            },
            {
                "asset": "ROCK",
                "id": -1,
                "lifetime": -1,
                "occupant": "NONE",
                "temporary_asset": "NONE",
                "type": "OBSTACLE"
            },
            {
                "asset": "IMPASSABLE",
                "id": -1,
                "lifetime": -1,
                "occupant": "NONE",
                "temporary_asset": "NONE",
                "type": "ENEMY PASSABLE"
            },
            {
                "asset": "IMPASSABLE",
                "id": -1,
                "lifetime": -1,
                "occupant": "NONE",
                "temporary_asset": "NONE",
                "type": "ENEMY PASSABLE"
            },
            {
                "asset": "IMPASSABLE",
                "id": -1,
                "lifetime": -1,
                "occupant": "NONE",
                "temporary_asset": "NONE",
                "type": "ENEMY PASSABLE"
            }
        ],
        [
            {
                "asset": "ROCK",
                "id": -1,
                "lifetime": -1,
                "occupant": "NONE",
                "temporary_asset": "NONE",
                "type": "OBSTACLE"
            },
            {
                "asset": "ROCK",
                "id": -1,
                "lifetime": -1,
                "occupant": "NONE",
                "temporary_asset": "NONE",
                "type": "OBSTACLE"
            },
            {
                "asset": "NONE",
                "id": -1,
                "lifetime": -1,
                "occupant": "NONE",
                "temporary_asset": "NONE",
                "type": "PASSABLE"
            },
            {
                "asset": "NONE",
                "id": -1,
                "lifetime": -1,
                "occupant": "NONE",
                "temporary_asset": "NONE",
                "type": "PASSABLE"
            },
            {
                "asset": "IMPASSABLE",
                "id": -1,
                "lifetime": -1,
                "occupant": "NONE",
                "temporary_asset": "NONE",
                "type": "ENEMY PASSABLE"
            },
            {
                "asset": "IMPASSABLE",
                "id": -1,
                "lifetime": -1,
                "occupant": "NONE",
                "temporary_asset": "NONE",
                "type": "ENEMY PASSABLE"
            },
            {
                "asset": "IMPASSABLE",
                "id": -1,
                "lifetime": -1,
                "occupant": "NONE",
                "temporary_asset": "NONE",
                "type": "ENEMY PASSABLE"
            }
        ]
    ],
    "tilesize": 64,
    "viewx": 7,
    "viewy": 12,
    "width": 7,
    "x": 0,
    "y": 0
}