{
    "location": {
        "book": "BOOK1",
        "number": 407
    },
    "text": "You rush down the narrow path that leads to the platform. The DIRGES caw angrily and veer to inctercept you. You just reach the ledge as they close to attack.",
    "battle": "modules/default/battles/battle407.json",
    "next": [
        {
            "type": "TEXTBOX",
            "location": {
                "book": "BOOK1",
                "number": 142
            },
            "variables": [
                "You continue down the ledge to the platform.",
                "INACTIVE"
            ]
        }
    ]
}